src/__init__.py
src/__main__.py
src/auth.py
src/config.py
src/logging_config.py
src/models.py
src/priority_client.py
src/server.py
taskpriority_mcp-1.2.0.dist-info/METADATA
taskpriority_mcp-1.2.0.dist-info/WHEEL
taskpriority_mcp-1.2.0.dist-info/entry_points.txt
taskpriority_mcp-1.2.0.dist-info/top_level.txt
taskpriority_mcp-1.2.0.dist-info/RECORD
