Metadata-Version: 2.4
Name: taskpriority-mcp
Version: 1.2.0
Summary: MCP server for intelligent task prioritization with Claude Desktop
Home-page: https://github.com/greenblat17/mcp-priority
Author: TaskPriority Team
Author-email: TaskPriority Team <support@taskpriority.ai>
License: MIT
Project-URL: Homepage, https://github.com/yourusername/mcp-priority
Project-URL: Documentation, https://github.com/yourusername/mcp-priority#readme
Project-URL: Repository, https://github.com/yourusername/mcp-priority.git
Project-URL: Issues, https://github.com/yourusername/mcp-priority/issues
Keywords: mcp,claude,taskpriority,ai,task-management
Classifier: Development Status :: 4 - Beta
Classifier: Intended Audience :: Developers
Classifier: License :: OSI Approved :: MIT License
Classifier: Operating System :: OS Independent
Classifier: Programming Language :: Python :: 3
Classifier: Programming Language :: Python :: 3.10
Classifier: Programming Language :: Python :: 3.11
Classifier: Programming Language :: Python :: 3.12
Classifier: Topic :: Software Development :: Libraries :: Python Modules
Requires-Python: >=3.10
Requires-Dist: mcp>=1.0.0
Requires-Dist: httpx>=0.28.0
Requires-Dist: pydantic>=2.0.0
Requires-Dist: pydantic-settings>=2.0.0
Requires-Dist: python-dotenv>=1.0.0
Requires-Dist: typing-extensions>=4.0.0
Dynamic: author
Dynamic: home-page
Dynamic: requires-python
